Workbook

Sheet Cover
A1: FLUENCE ENERGY, INC. (NASDAQ: FLNC) INITIATION MODEL
A2: Tommy Lau | Fluence Energy (Nasdaq: FLNC) | 12 October 2026 | Personal research, not investment advice.
A4: Item | B4: Value | C4: Note
A5: Call (Tommy Lau) | B5: NO CALL | C5: Applied on the band to the base value: LONG at +15% or more, SHORT at -25% or worse, NO CALL between.
A6: Base value per share, US$ | B6: =Valuation!$B$10 -> 7.8818343 | C6: 0.45x FY28E revenue less estimated net debt, over Class A plus Class B-1 shares.
A7: Reference price, US$ | B7: =Assumptions!$B$7 -> 7.43 | C7: Nasdaq close, 9 October 2026.
A8: Base value against price | B8: =Valuation!$B$12 -> 0.060812159
A9: Probability-weighted value, US$ | B9: =Scenarios!E11 -> 8.4701449 | C9: 25 / 50 / 25 bear / base / bull.
A10: Conviction | B10: Medium | C10: Judgement, not formula.
A11: Horizon | B11: 12 months, to October 2027
A12: Revisit if | B12: See note | C12: A price below about US$6.85, where my base value would sit 15 per cent above it, or Fluence's first quarterly American production figures, due with its fiscal 2026 results, showing Houston at or near its planned 11 units a day alongside a fiscal 2027 plan of at least US$3.0 billion of revenue.
A13: Wrong if | B13: See note | C13: The shares close above US$11.00 or below US$4.50 in October 2027, or the fiscal 2027 plan Fluence publishes with its fiscal 2026 results puts revenue below US$2.6 billion or above US$3.5 billion.
A16: Tabs
A17: Assumptions | B17: Every input, with its source. Change the yellow cells to move the value.
A18: Financials | B18: FY24A to FY28E: revenue, adjusted gross profit, net operating costs, adjusted EBITDA, EV multiples.
A19: Valuation | B19: Base value, the band, what the price needs, cross-checks, net debt.
A20: Scenarios | B20: Bear / base / bull and the probability-weighted value.
A21: Sensitivity | B21: FY28E revenue against EV/revenue multiple.
A22: Quarters | B22: Quarterly results, backlog, the nine months to June 2026, the implied September quarter, demand indicators.
A23: Peers | B23: EV/sales and EV/EBITDA used to set the multiple.
A24: Sources | B24: Every source used.
A26: Colour key: blue = hardcoded input; yellow fill = my own assumption; green = link to another tab; black = formula.
A27: Companion note: 2026-10-12_Fluence_Initiation.pdf. Personal research, not investment advice.

Sheet Assumptions
A1: ASSUMPTIONS AND INPUTS
A2: Tommy Lau | Fluence Energy (Nasdaq: FLNC) | 12 October 2026 | Personal research, not investment advice.
A3: Blue = hardcoded input. Yellow fill = my own assumption (change these to move the value). Green = link to another tab. Black = formula. US$ million unless stated. Fiscal years end 30 September.
A5: Input | B5: Value | C5: Unit | D5: Source / note
A6: MARKET
A7: Reference share price | B7: 7.43 | C7: US$ | D7: Nasdaq close, 9 October 2026. Nasdaq.com historical data, retrieved 12 October 2026.
A8: Highest close, 3 February 2026 | B8: 32.23 | C8: US$ | D8: Nasdaq.com historical data. Intraday high US$33.51 on 30 January 2026.
A9: Class A shares outstanding, 31 July 2026 | B9: 143.16359 | C9: m | D9: Form 10-Q for the quarter to 30 June 2026, cover page: 143,163,588.
A10: Class B-1 shares outstanding, 31 July 2026 | B10: 41.432781 | C10: m | D10: Form 10-Q cover: 41,432,781, held by AES Grid Stability; redeemable for Class A one for one.
A11: Cash, cash equivalents and restricted cash, 30 June 2026 | B11: 364.958 | C11: US$m | D11: Form 10-Q balance sheet: 339.328 + 25.630.
A12: 2.25% convertible senior notes due 2030, principal | B12: 400 | C12: US$m | D12: Form 10-Q, Note 12. Conversion price about US$21.35; treated as debt.
A13: Cash used in the September 2026 quarter | B13: 130 | C13: US$m | D13: MY ASSUMPTION. Not yet reported. Close to the minus US$133m implied by the S&P Global full-year free cash flow forecast less the nine-month actual.
A14: Free cash flow, nine months to 30 June 2026 | B14: -299.026 | C14: US$m | D14: 3Q FY26 results release (company definition).
A15: FY26 free cash flow, consensus | B15: -431.93 | C15: US$m | D15: stockanalysis.com (S&P Global), retrieved 12 October 2026. Cross-check only.
A16: FY27 revenue, consensus | B16: 3250 | C16: US$m | D16: stockanalysis.com (S&P Global), retrieved 12 October 2026. Cross-check only.
A17: Average analyst target | B17: 10 | C17: US$ | D17: stockanalysis.com, 23 analysts; median US$8.50, low US$3, high US$23. Cross-check only.
A18: REPORTED (fiscal years to 30 September)
A19: FY24 revenue | B19: 2698.562 | C19: US$m | D19: 4Q and FY25 results release (Form 8-K, Exhibit 99.1), 24 November 2025.
A20: FY25 revenue | B20: 2262.83 | C20: US$m | D20: Same release.
A21: FY24 adjusted gross profit | B21: 347.856 | C21: US$m | D21: Same release, non-GAAP reconciliation.
A22: FY25 adjusted gross profit | B22: 309.538 | C22: US$m | D22: Same release.
A23: FY24 adjusted EBITDA | B23: 78.106 | C23: US$m | D23: Same release.
A24: FY25 adjusted EBITDA | B24: 19.455 | C24: US$m | D24: Same release.
A25: FY24 free cash flow | B25: 71.57 | C25: US$m | D25: Same release.
A26: FY25 free cash flow | B26: -160.422 | C26: US$m | D26: Same release.
A27: GUIDANCE FOR FY26 (Form 8-K, 16 September 2026)
A28: FY26 revenue guide | B28: 2400 | C28: US$m | D28: About US$2.4bn. Was US$2.9 to 3.1bn (5 August 2026) and US$3.2 to 3.6bn (24 November 2025).
A29: FY26 adjusted EBITDA guide | B29: -200 | C29: US$m | D29: A loss of about US$200m. Was minus US$30m to plus US$10m (5 August) and US$40 to 60m (24 November 2025).
A30: FY26 revenue guide midpoint, November 2025 | B30: 3400 | C30: US$m | D30: 4Q and FY25 results release.
A31: MY ASSUMPTIONS
A32: FY27 revenue growth | B32: 0.25 | C32: % | D32: MY ASSUMPTION. Below the S&P Global consensus of US$3.25bn: US$2.2bn of backlog was scheduled for FY27 at the August call, and Houston must work for the rest.
A33: FY28 revenue growth | B33: 0.2 | C33: % | D33: MY ASSUMPTION. Backlog of US$6.4bn and record orders support it once delivery runs on time.
A34: FY27 adjusted gross margin | B34: 0.105 | C34: % | D34: MY ASSUMPTION. Penalties and launch costs fade through the year.
A35: FY28 adjusted gross margin | B35: 0.13 | C35: % | D35: MY ASSUMPTION. Back to about the 12.9% to 13.7% of FY24 and FY25.
A36: FY27 net operating costs (adjusted gross profit less adjusted EBITDA) | B36: 295 | C36: US$m | D36: MY ASSUMPTION. US$270m in FY24, US$290m in FY25, US$208m in the nine months to June 2026 (Quarters tab).
A37: FY28 net operating costs | B37: 320 | C37: US$m | D37: MY ASSUMPTION. Grows with volume.
A38: EV / FY28E revenue, base | B38: 0.45 | C38: x | D38: MY ASSUMPTION. About 11x my FY28 EBITDA, below the peer median of 13x trailing EV/EBITDA; see Peers.

Sheet Financials
A1: FINANCIAL SUMMARY AND FORECASTS (US$ million unless stated; fiscal years to 30 September)
A2: Tommy Lau | Fluence Energy (Nasdaq: FLNC) | 12 October 2026 | Personal research, not investment advice.
B4: FY24A | C4: FY25A | D4: FY26 guide | E4: FY27E* | F4: FY28E*
A5: Revenue | B5: =Assumptions!$B$19 -> 2698.562 | C5: =Assumptions!$B$20 -> 2262.83 | D5: =Assumptions!$B$28 -> 2400 | E5: =D5*(1+Assumptions!$B$32) -> 3000 | F5: =E5*(1+Assumptions!$B$33) -> 3600
A6: Revenue growth | C6: =C5/B5-1 -> -0.16146822 | D6: =D5/C5-1 -> 0.060618783 | E6: =E5/D5-1 -> 0.25 | F6: =F5/E5-1 -> 0.2
A7: Adjusted gross margin | B7: =B8/B5 -> 0.12890421 | C7: =C8/C5 -> 0.13679242 | E7: =Assumptions!$B$34 -> 0.105 | F7: =Assumptions!$B$35 -> 0.13
A8: Adjusted gross profit | B8: =Assumptions!$B$21 -> 347.856 | C8: =Assumptions!$B$22 -> 309.538 | E8: =E5*E7 -> 315 | F8: =F5*F7 -> 468
A9: Net operating costs (adjusted gross profit less adjusted EBITDA) | B9: =B8-B10 -> 269.75 | C9: =C8-C10 -> 290.083 | E9: =Assumptions!$B$36 -> 295 | F9: =Assumptions!$B$37 -> 320
A10: Adjusted EBITDA | B10: =Assumptions!$B$23 -> 78.106 | C10: =Assumptions!$B$24 -> 19.455 | D10: =Assumptions!$B$29 -> -200 | E10: =E8-E9 -> 20 | F10: =F8-F9 -> 148
A11: Adjusted EBITDA margin | B11: =B10/B5 -> 0.028943563 | C11: =C10/C5 -> 0.008597641 | D11: =D10/D5 -> -0.083333333 | E11: =E10/E5 -> 0.0066666667 | F11: =F10/F5 -> 0.041111111
A12: Free cash flow | B12: =Assumptions!$B$25 -> 71.57 | C12: =Assumptions!$B$26 -> -160.422
A13: EV / revenue at reference price | D13: =Valuation!$B$16/D5 -> 0.64024709 | E13: =Valuation!$B$16/E5 -> 0.51219767 | F13: =Valuation!$B$16/F5 -> 0.42683139
A14: EV / adjusted EBITDA at reference price | E14: =Valuation!$B$16/E10 -> 76.829651 | F14: =Valuation!$B$16/F10 -> 10.382385
A17: *FY27E and FY28E are my own estimates, not Fluence's. FY26 is Fluence's own guide of 16 September 2026; it gives no gross margin guide.
A18: Adjusted gross profit and adjusted EBITDA are Fluence's non-GAAP measures. Net operating costs is my derived line: adjusted gross profit less adjusted EBITDA.
A19: EV uses my estimate of net debt at 30 September 2026 (Valuation tab). Fluence has given no guidance beyond FY26; its FY27 plan is due with the FY26 results.

Sheet Valuation
A1: VALUATION: EV / FY28E REVENUE, TWELVE MONTHS OUT
A2: Tommy Lau | Fluence Energy (Nasdaq: FLNC) | 12 October 2026 | Personal research, not investment advice.
A4: Line | B4: Value | C4: Working / note
A5: FY28E revenue, US$m | B5: =Financials!F5 -> 3600 | C5: Financials tab. By October 2027 the market will be pricing the year to September 2028.
A6: Multiple, x revenue | B6: =Assumptions!$B$38 -> 0.45 | C6: Assumptions tab.
A7: Enterprise value at the base multiple, US$m | B7: =B5*B6 -> 1620 | C7: Revenue x multiple.
A8: Less net debt, estimated at 30 September 2026, US$m | B8: =Assumptions!$B$12-Assumptions!$B$11+Assumptions!$B$13 -> 165.042 | C8: Convertible principal less June cash, plus my estimate of September quarter cash use. Held flat: Fluence aims for neutral to positive operating cash flow in FY27.
A9: Shares, Class A plus Class B-1, m | B9: =Assumptions!$B$9+Assumptions!$B$10 -> 184.59637 | C9: Economic shares. Convertible far out of the money; no dilution assumed.
A10: BASE VALUE PER SHARE, US$ | B10: =(B7-B8)/B9 -> 7.8818343 | C10: Equity value / shares.
A11: Reference price, US$ | B11: =Assumptions!$B$7 -> 7.43 | C11: Nasdaq close, 9 October 2026.
A12: Base value against price | B12: =B10/B11-1 -> 0.060812159 | C12: Band: LONG at +15% or more, SHORT at -25% or worse, NO CALL between.
A13: VIEW ON THE BAND | B13: =IF(B12>=0.15,"LONG",IF(B12<=-0.25,"SHORT","NO CALL")) -> NO CALL | C13: Band rule on the base value. Tommy Lau's call: NO CALL.
A15: Market value, US$m | B15: =B9*B11 -> 1371.551 | C15: Price x shares.
A16: Enterprise value, US$m | B16: =B15+B8 -> 1536.593 | C16: Market value plus estimated net debt.
A17: FY28 revenue the price needs at the base multiple, US$m | B17: =B16/B6 -> 3414.6512 | C17: Compare with my FY28E (B5) and FY27 consensus.
A18: That figure against my FY28E | B18: =B17/B5 -> 0.94851421
A19: EV / FY26 revenue guide | B19: =B16/Financials!D5 -> 0.64024709
A20: EV / FY27 consensus revenue | B20: =B16/Assumptions!$B$16 -> 0.47279785 | C20: Cross-check only.
A21: EV / FY28E revenue | B21: =B16/B5 -> 0.42683139
A22: EV / FY28E adjusted EBITDA | B22: =B16/Financials!F10 -> 10.382385
A23: Base case EV / FY28E adjusted EBITDA | B23: =B7/Financials!F10 -> 10.945946 | C23: The base revenue multiple expressed on EBITDA; compare Peers.
A24: Price at which the base value is 15% above it, US$ | B24: =B10/1.15 -> 6.853769 | C24: Revisit level for a LONG.
A25: Price at which the base value is 25% below it, US$ | B25: =B10/0.75 -> 10.509112 | C25: Revisit level for a SHORT.
A26: Price against highest close | B26: =B11/Assumptions!$B$8-1 -> -0.76946944 | C26: Highest close US$32.23, 3 February 2026.
A27: Net debt at 30 June 2026, US$m | B27: =Assumptions!$B$12-Assumptions!$B$11 -> 35.042 | C27: Reported basis.
A28: Consensus-implied free cash flow, September 2026 quarter, US$m | B28: =Assumptions!$B$15-Assumptions!$B$14 -> -132.904 | C28: Cross-check for my September quarter cash use.
A29: FY26 revenue guide against the November 2025 midpoint | B29: =Financials!D5/Assumptions!$B$30-1 -> -0.29411765

Sheet Scenarios
A1: THREE CASES, TWELVE MONTHS OUT
A2: Tommy Lau | Fluence Energy (Nasdaq: FLNC) | 12 October 2026 | Personal research, not investment advice.
A4: Case | B4: FY27 growth | C4: FY28 growth | D4: FY28 adj. gross margin | E4: EV/sales | F4: FY27 revenue | G4: FY28 revenue | H4: FY28 adj. EBITDA | I4: EV/EBITDA | J4: Value, US$ | K4: vs price
A5: Bear | B5: 0.1 | C5: 0.1 | D5: 0.12 | E5: 0.25 | F5: =Financials!$D$5*(1+B5) -> 2640 | G5: =F5*(1+C5) -> 2904 | H5: =G5*D5-Assumptions!$B$37 -> 28.48 | I5: =G5*E5/H5 -> 25.491573 | J5: =(G5*E5-Valuation!$B$8)/Valuation!$B$9 -> 3.0388355 | K5: =J5/Assumptions!$B$7-1 -> -0.59100464
A6: Base | B6: =Assumptions!$B$32 -> 0.25 | C6: =Assumptions!$B$33 -> 0.2 | D6: =Assumptions!$B$35 -> 0.13 | E6: =Assumptions!$B$38 -> 0.45 | F6: =Financials!$D$5*(1+B6) -> 3000 | G6: =F6*(1+C6) -> 3600 | H6: =G6*D6-Assumptions!$B$37 -> 148 | I6: =G6*E6/H6 -> 10.945946 | J6: =(G6*E6-Valuation!$B$8)/Valuation!$B$9 -> 7.8818343 | K6: =J6/Assumptions!$B$7-1 -> 0.060812159
A7: Bull | B7: 0.35 | C7: 0.3 | D7: 0.145 | E7: 0.7 | F7: =Financials!$D$5*(1+B7) -> 3240 | G7: =F7*(1+C7) -> 4212 | H7: =G7*D7-Assumptions!$B$37 -> 290.74 | I7: =G7*E7/H7 -> 10.141019 | J7: =(G7*E7-Valuation!$B$8)/Valuation!$B$9 -> 15.078076 | K7: =J7/Assumptions!$B$7-1 -> 1.0293507
B8: Bear | C8: Base | D8: Bull
A9: Probability | B9: 0.25 | C9: 0.5 | D9: 0.25 | E9: =SUM(B9:D9) -> 1 | F9: must be 100%
A11: Probability-weighted value, US$ | E11: =B9*J5+C9*J6+D9*J7 -> 8.4701449 | F11: =E11/Assumptions!$B$7-1 -> 0.13999259
A13: All cases start from the FY26 revenue guide of about US$2.4bn, use my FY28 net operating costs (Assumptions) for the EBITDA cross-check,
A14: and take off the same estimated net debt over the same shares. Bear: Houston stays slow into 2027 and the FY27 plan is cut again; the bear multiple
A15: prices a company with almost no earnings and a cash question, so its EV/EBITDA is not meaningful. Bull: Houston fixed early in 2027 and data centre
A16: awards become orders; the bull multiple is about 10x FY28 EBITDA.

Sheet Sensitivity
A1: VALUE PER SHARE: FY28E REVENUE AGAINST EV / REVENUE MULTIPLE (US$)
A2: Tommy Lau | Fluence Energy (Nasdaq: FLNC) | 12 October 2026 | Personal research, not investment advice.
A4: FY28 revenue (US$m) \ multiple | B4: 0.35 | C4: =Assumptions!$B$38 -> 0.45 | D4: 0.55
A5: 3000 | B5: =($A5*B$4-Valuation!$B$8)/Valuation!$B$9 -> 4.7940163 | C5: =($A5*C$4-Valuation!$B$8)/Valuation!$B$9 -> 6.4191837 | D5: =($A5*D$4-Valuation!$B$8)/Valuation!$B$9 -> 8.0443511
A6: =Financials!F5 -> 3600 | B6: =($A6*B$4-Valuation!$B$8)/Valuation!$B$9 -> 5.9316335 | C6: =($A6*C$4-Valuation!$B$8)/Valuation!$B$9 -> 7.8818343 | D6: =($A6*D$4-Valuation!$B$8)/Valuation!$B$9 -> 9.8320352
A7: 4200 | B7: =($A7*B$4-Valuation!$B$8)/Valuation!$B$9 -> 7.0692506 | C7: =($A7*C$4-Valuation!$B$8)/Valuation!$B$9 -> 9.344485 | D7: =($A7*D$4-Valuation!$B$8)/Valuation!$B$9 -> 11.619719
A9: Cells above the reference price | B9: =COUNTIF(B5:D7,">"&Assumptions!$B$7) -> 5 | C9: of 9
A10: Cells 15% or more above the price | B10: =COUNTIF(B5:D7,">="&Assumptions!$B$7*1.15) -> 3 | C10: of 9
A12: Middle row links to the model's FY28E revenue and the middle column to the base multiple, so the grid moves with the assumptions.

Sheet Quarters
A1: QUARTERLY RESULTS, BACKLOG AND THE FY26 CUTS (US$ million unless stated)
A2: Tommy Lau | Fluence Energy (Nasdaq: FLNC) | 12 October 2026 | Personal research, not investment advice.
A4: Quarter (fiscal year to 30 September) | B4: Q1 FY25 | C4: Q2 FY25 | D4: Q3 FY25 | E4: Q4 FY25 | F4: Q1 FY26 | G4: Q2 FY26 | H4: Q3 FY26
A5: Revenue | B5: 186.788 | C5: 431.618 | D5: 602.533 | E5: 1041.891 | F5: 475.234 | G5: 464.891 | H5: 649.848
A6: GAAP gross profit | B6: 21.201 | C6: 42.582 | D6: 89.099 | E6: 142.903 | F6: 23.049 | G6: 46.63 | H6: 33.241
A7: GAAP gross margin (derived) | B7: =B6/B5 -> 0.11350301 | C7: =C6/C5 -> 0.098656683 | D7: =D6/D5 -> 0.14787406 | E7: =E6/E5 -> 0.13715734 | F7: =F6/F5 -> 0.048500318 | G7: =G6/G5 -> 0.10030308 | H7: =H6/H5 -> 0.051151962
A8: Adjusted gross margin, as reported | B8: 0.125 | C8: 0.104 | D8: 0.154 | E8: 0.143 | F8: 0.056 | G8: 0.111 | H8: 0.059
A9: Adjusted EBITDA | B9: -49.676 | C9: -30.411 | D9: 27.355 | E9: 72.187 | F9: -52.058 | G9: -9.442 | H9: -29.296
A10: Backlog at quarter end, US$bn | B10: 5.1 | C10: 4.9 | D10: 4.9 | E10: 5.3 | F10: 5.5 | G10: 5.6 | H10: 6.4
A12: Nine months to 30 June 2026
A13: Revenue | B13: =SUM(F5:H5) -> 1589.973
A14: Adjusted gross profit (reported) | B14: 116.772
A15: Adjusted EBITDA | B15: =SUM(F9:H9) -> -90.796
A16: Net operating costs (derived) | B16: =B14-B15 -> 207.568
A17: Revenue from customers in the Americas | B17: 890.926
A18: Americas share of revenue | B18: =B17/B13 -> 0.56034033
A20: September 2026 quarter implied by the FY26 guide
A21: Revenue | B21: =Assumptions!$B$28-B13 -> 810.027
A22: Adjusted EBITDA | B22: =Assumptions!$B$29-B15 -> -109.204
A24: Demand indicators (Form 10-Q)
A25: Metric | B25: Latest | C25: Year earlier | D25: Change
A26: Storage contracted, nine months, GW | B26: 4.2 | C26: 1.9 | D26: =B26/C26-1 -> 1.2105263
A27: Storage pipeline, GWh (30 Jun 2026 vs 30 Sep 2025) | B27: 163.7 | C27: 122 | D27: =B27/C27-1 -> 0.34180328
A29: Sources: Fluence quarterly results releases, 10 February 2025 to 5 August 2026; Form 10-Q for the quarter to 30 June 2026 (revenue by region,
A30: key operating metrics). Adjusted gross margin as first reported in each release. Order intake in US$: 778.0 (Dec 24), 200.0 (Mar 25), 508.8 (Jun 25),
A31: over 1,400 (Sep 25), over 750 (Dec 25), over 1,440 (Jun 26); the March 2026 quarter was not given on its own.

Sheet Peers
A1: PEER MULTIPLES (stockanalysis.com, RETRIEVED 12 OCTOBER 2026; TRAILING)
A2: Tommy Lau | Fluence Energy (Nasdaq: FLNC) | 12 October 2026 | Personal research, not investment advice.
A4: Company | B4: Ticker | C4: EV/sales | D4: EV/EBITDA | E4: What they make
A5: Fluence | B5: Nasdaq: FLNC | C5: 0.55 | D5: n.m. | E5: Grid battery systems, services and control software (integrator)
A6: Sungrow | B6: SZSE: 300274 | C6: 1.84 | D6: 10.04 | E6: Inverters and grid battery systems
A7: Nextracker | B7: Nasdaq: NXT | C7: 3.28 | D7: 15.88 | E7: Solar trackers
A8: Shoals | B8: Nasdaq: SHLS | C8: 2.87 | D8: 16.79 | E8: Electrical balance of system for solar and storage
A9: Array Technologies | B9: Nasdaq: ARRY | C9: 0.85 | D9: 8.48 | E9: Solar trackers
A10: Eos Energy | B10: Nasdaq: EOSE | C10: 5.85 | D10: n.m. | E10: Zinc-based long-duration batteries
A12: Peer median (four peers with positive EBITDA; excludes Fluence and Eos Energy) | C12: =MEDIAN(C6:C9) -> 2.355 | D12: =MEDIAN(D6:D9) -> 12.96
A13: Fluence base case on FY28E EBITDA | D13: =Valuation!B23 -> 10.945946
A15: Multiples only, to set the range. No view on the peers' shares is expressed. n.m. = not meaningful (negative EBITDA).
A16: Fluence's own trailing EV/sales as computed by stockanalysis.com; the model's EV uses my net debt estimate.

Sheet Sources
A1: SOURCES
A2: Tommy Lau | Fluence Energy (Nasdaq: FLNC) | 12 October 2026 | Personal research, not investment advice.
A4: No. | B4: Source and what it supports
A5: 1 | B5: Fluence quarterly results releases, Form 8-K Exhibit 99.1: 10 February 2025, 7 May 2025, 11 August 2025, 24 November 2025 (FY25 and first FY26 guide), 4 February 2026, 6 May 2026, 5 August 2026 (first FY26 cut). Revenue, gross and adjusted gross profit, adjusted EBITDA, free cash flow, orders, backlog, liquidity.
A6: 2 | B6: Fluence Form 8-K of 16 September 2026, Exhibit 99.1 (revised FY26 guide; Houston named as the primary reason; plans to report US production, actual and forecast; FY27 plan with FY26 results) and Exhibit 99.2 (Bernerd Da Santos as chief operating officer).
A7: 3 | B7: Fluence Form 10-Q for the quarter to 30 June 2026, filed 5 August 2026: balance sheet, shares, convertible notes (Note 12), backlog conversion, key operating metrics, revenue by region, liquidated damages, credit agreement covenants, shelf registration, secondary offering.
A8: 4 | B8: Fluence Form 8-K of 15 May 2026 (AES redemption) and Form 8-K of 9 October 2026 (separation of the chief product officer).
A9: 5 | B9: Fluence third quarter fiscal 2026 earnings call, 6 August 2026, transcript published by The Motley Fool on 12 August 2026: Houston capacity and timing, generators, US$2.2bn of backlog scheduled for FY27, data centre pipeline and awards.
A10: 6 | B10: Latitude Media (21 September 2026), mgrid.org (18 September 2026) and the Quartr summary of the 16 September 2026 call: Houston unit rates, the American share of the cut, penalties, quarterly US production reporting. Not verified against the replay.
A11: 7 | B11: Nasdaq.com historical data, retrieved 12 October 2026: daily and month-end closes, highs and lows.
A12: 8 | B12: stockanalysis.com (S&P Global consensus), retrieved 12 October 2026: consensus revenue, free cash flow, targets, ratings, short interest, peer multiples.
A13: 9 | B13: The Physical Layer, 'Fluence has plenty of batteries. What it is short of is American-made ones', 12 October 2026: https://thephysicallayer.fyi/journal/fluence-short-of-american-made/
A14: 10 | B14: Estimates for FY27 and FY28 and the September 2026 quarter cash use are the author's own. Personal research, not investment advice.
